LICENSE.md
MANIFEST.in
README.rst
setup.py
ovp_testimonials/__init__.py
ovp_testimonials/admin.py
ovp_testimonials/apps.py
ovp_testimonials/helpers.py
ovp_testimonials/models.py
ovp_testimonials/serializers.py
ovp_testimonials/urls.py
ovp_testimonials/views.py
ovp_testimonials.egg-info/PKG-INFO
ovp_testimonials.egg-info/SOURCES.txt
ovp_testimonials.egg-info/dependency_links.txt
ovp_testimonials.egg-info/not-zip-safe
ovp_testimonials.egg-info/requires.txt
ovp_testimonials.egg-info/top_level.txt
ovp_testimonials/__pycache__/__init__.cpython-35.pyc
ovp_testimonials/__pycache__/admin.cpython-35.pyc
ovp_testimonials/__pycache__/apps.cpython-35.pyc
ovp_testimonials/__pycache__/helpers.cpython-35.pyc
ovp_testimonials/__pycache__/models.cpython-35.pyc
ovp_testimonials/__pycache__/serializers.cpython-35.pyc
ovp_testimonials/__pycache__/urls.cpython-35.pyc
ovp_testimonials/__pycache__/views.cpython-35.pyc
ovp_testimonials/migrations/0001_initial.py
ovp_testimonials/migrations/0002_testimonials.py
ovp_testimonials/migrations/0003_auto_20170426_1833.py
ovp_testimonials/migrations/0004_auto_20170426_1838.py
ovp_testimonials/migrations/0005_auto_20170426_1922.py
ovp_testimonials/migrations/0006_auto_20170426_1929.py
ovp_testimonials/migrations/__init__.py
ovp_testimonials/migrations/__pycache__/0001_initial.cpython-35.pyc
ovp_testimonials/migrations/__pycache__/0002_testimonials.cpython-35.pyc
ovp_testimonials/migrations/__pycache__/0003_auto_20170426_1833.cpython-35.pyc
ovp_testimonials/migrations/__pycache__/0004_auto_20170426_1838.cpython-35.pyc
ovp_testimonials/migrations/__pycache__/0005_auto_20170426_1922.cpython-35.pyc
ovp_testimonials/migrations/__pycache__/0006_auto_20170426_1929.cpython-35.pyc
ovp_testimonials/migrations/__pycache__/__init__.cpython-35.pyc
ovp_testimonials/tests/__init__.py
ovp_testimonials/tests/runtests.py
ovp_testimonials/tests/test_execution.py
ovp_testimonials/tests/test_views.py
ovp_testimonials/tests/__pycache__/__init__.cpython-35.pyc
ovp_testimonials/tests/__pycache__/test_execution.cpython-35.pyc
ovp_testimonials/tests/__pycache__/test_views.cpython-35.pyc