Metadata-Version: 1.1
Name: ovp-testimonials
Version: 1.0.0
Summary: This module has user testimonials functionality
Home-page: https://github.com/OpenVolunteeringPlatform/django-ovp-testimonials
Author: Atados
Author-email: arroyo@atados.com.br
License: AGPL
Download-URL: https://github.com/OpenVolunteeringPlatform/django-ovp-testimonials/tarball/1.0.0
Platform: UNKNOWN
